package org.bocai.decompiler.java;
/**
 * 每个指令的具体描述,参见：http://docs.oracle.com/javase/specs/jvms/se7/html/jvms-6.html
 * @author yikebocai@gmail.com
 * @since 2013-3-12
 *
 */
public class OperateCodes {
	public static final OperateCode[] opCodes=new OperateCode[256];
	static{

		opCodes[0]=new OperateCode( "nop");
		opCodes[1]=new OperateCode( "aconst_null");
		opCodes[2]=new OperateCode( "iconst_m1");
		opCodes[3]=new OperateCode( "iconst_0");
		opCodes[4]=new OperateCode( "iconst_1");
		opCodes[5]=new OperateCode( "iconst_2");
		opCodes[6]=new OperateCode( "iconst_3");
		opCodes[7]=new OperateCode( "iconst_4");
		opCodes[8]=new OperateCode( "iconst_5");
		opCodes[9]=new OperateCode( "lconst_0");
		opCodes[10]=new OperateCode( "lconst_1");
		opCodes[11]=new OperateCode( "fconst_0");
		opCodes[12]=new OperateCode( "fconst_1");
		opCodes[13]=new OperateCode( "fconst_2");
		opCodes[14]=new OperateCode( "dconst_0");
		opCodes[15]=new OperateCode( "dconst_1");
		opCodes[16]=new OperateCode( "bipush",OperandType.INT_VALUE,1);
		opCodes[17]=new OperateCode( "sipush",OperandType.INT_VALUE,2);
		opCodes[18]=new OperateCode( "ldc",OperandType.CONSTANT_POOL_INDEX,1);
		opCodes[19]=new OperateCode( "ldc_w",OperandType.CONSTANT_POOL_INDEX,2);
		opCodes[20]=new OperateCode( "ldc2_w",OperandType.CONSTANT_POOL_INDEX,2);
		opCodes[21]=new OperateCode( "iload",OperandType.LOCAL_VARIABLES_INDEX,1);
		opCodes[22]=new OperateCode( "lload",OperandType.LOCAL_VARIABLES_INDEX,1);
		opCodes[23]=new OperateCode( "fload",OperandType.LOCAL_VARIABLES_INDEX,1);
		opCodes[24]=new OperateCode( "dload",OperandType.LOCAL_VARIABLES_INDEX,1);
		opCodes[25]=new OperateCode( "aload",OperandType.LOCAL_VARIABLES_INDEX,1);
		opCodes[26]=new OperateCode( "iload_0");
		opCodes[27]=new OperateCode( "iload_1");
		opCodes[28]=new OperateCode( "iload_2");
		opCodes[29]=new OperateCode( "iload_3");
		opCodes[30]=new OperateCode( "lload_0");
		opCodes[31]=new OperateCode( "lload_1");
		opCodes[32]=new OperateCode( "lload_2");
		opCodes[33]=new OperateCode( "lload_3");
		opCodes[34]=new OperateCode( "fload_0");
		opCodes[35]=new OperateCode( "fload_1");
		opCodes[36]=new OperateCode( "fload_2");
		opCodes[37]=new OperateCode( "fload_3");
		opCodes[38]=new OperateCode( "dload_0");
		opCodes[39]=new OperateCode( "dload_1");
		opCodes[40]=new OperateCode( "dload_2");
		opCodes[41]=new OperateCode( "dload_3");
		opCodes[42]=new OperateCode( "aload_0");
		opCodes[43]=new OperateCode( "aload_1");
		opCodes[44]=new OperateCode( "aload_2");
		opCodes[45]=new OperateCode( "aload_3");
		opCodes[46]=new OperateCode( "iaload");
		opCodes[47]=new OperateCode( "laload");
		opCodes[48]=new OperateCode( "faload");
		opCodes[49]=new OperateCode( "daload");
		opCodes[50]=new OperateCode( "aaload");
		opCodes[51]=new OperateCode( "baload");
		opCodes[52]=new OperateCode( "caload");
		opCodes[53]=new OperateCode( "saload");
		opCodes[54]=new OperateCode( "istore",OperandType.LOCAL_VARIABLES_INDEX,1);
		opCodes[55]=new OperateCode( "lstore",OperandType.LOCAL_VARIABLES_INDEX,1);
		opCodes[56]=new OperateCode( "fstore",OperandType.LOCAL_VARIABLES_INDEX,1);
		opCodes[57]=new OperateCode( "dstore",OperandType.LOCAL_VARIABLES_INDEX,1);
		opCodes[58]=new OperateCode( "astore",OperandType.LOCAL_VARIABLES_INDEX,1);
		opCodes[59]=new OperateCode( "istore_0");
		opCodes[60]=new OperateCode( "istore_1");
		opCodes[61]=new OperateCode( "istore_2");
		opCodes[62]=new OperateCode( "istore_3");
		opCodes[63]=new OperateCode( "lstore_0");
		opCodes[64]=new OperateCode( "lstore_1");
		opCodes[65]=new OperateCode( "lstore_2");
		opCodes[66]=new OperateCode( "lstore_3");
		opCodes[67]=new OperateCode( "fstore_0");
		opCodes[68]=new OperateCode( "fstore_1");
		opCodes[69]=new OperateCode( "fstore_2");
		opCodes[70]=new OperateCode( "fstore_3");
		opCodes[71]=new OperateCode( "dstore_0");
		opCodes[72]=new OperateCode( "dstore_1");
		opCodes[73]=new OperateCode( "dstore_2");
		opCodes[74]=new OperateCode( "dstore_3");
		opCodes[75]=new OperateCode( "astore_0");
		opCodes[76]=new OperateCode( "astore_1");
		opCodes[77]=new OperateCode( "astore_2");
		opCodes[78]=new OperateCode( "astore_3");
		opCodes[79]=new OperateCode( "iastore");
		opCodes[80]=new OperateCode( "lastore");
		opCodes[81]=new OperateCode( "fastore");
		opCodes[82]=new OperateCode( "dastore");
		opCodes[83]=new OperateCode( "aastore");
		opCodes[84]=new OperateCode( "bastore");
		opCodes[85]=new OperateCode( "castore");
		opCodes[86]=new OperateCode( "sastore");
		opCodes[87]=new OperateCode( "pop");
		opCodes[88]=new OperateCode( "pop2");
		opCodes[89]=new OperateCode( "dup");
		opCodes[90]=new OperateCode( "dup_x1");
		opCodes[91]=new OperateCode( "dup_x2");
		opCodes[92]=new OperateCode( "dup2");
		opCodes[93]=new OperateCode( "dup2_x1");
		opCodes[94]=new OperateCode( "dup2_x2");
		opCodes[95]=new OperateCode( "swap");
		opCodes[96]=new OperateCode( "iadd");
		opCodes[97]=new OperateCode( "ladd");
		opCodes[98]=new OperateCode( "fadd");
		opCodes[99]=new OperateCode( "dadd");
		opCodes[100]=new OperateCode( "isub");
		opCodes[101]=new OperateCode( "lsub");
		opCodes[102]=new OperateCode( "fsub");
		opCodes[103]=new OperateCode( "dsub");
		opCodes[104]=new OperateCode( "imul");
		opCodes[105]=new OperateCode( "lmul");
		opCodes[106]=new OperateCode( "fmul");
		opCodes[107]=new OperateCode( "dmul");
		opCodes[108]=new OperateCode( "idiv");
		opCodes[109]=new OperateCode( "ldiv");
		opCodes[110]=new OperateCode( "fdiv");
		opCodes[111]=new OperateCode( "ddiv");
		opCodes[112]=new OperateCode( "irem");
		opCodes[113]=new OperateCode( "lrem");
		opCodes[114]=new OperateCode( "frem");
		opCodes[115]=new OperateCode( "drem");
		opCodes[116]=new OperateCode( "ineg");
		opCodes[117]=new OperateCode( "lneg");
		opCodes[118]=new OperateCode( "fneg");
		opCodes[119]=new OperateCode( "dneg");
		opCodes[120]=new OperateCode( "ishl");
		opCodes[121]=new OperateCode( "lshl");
		opCodes[122]=new OperateCode( "ishr");
		opCodes[123]=new OperateCode( "lshr");
		opCodes[124]=new OperateCode( "iushr");
		opCodes[125]=new OperateCode( "lushr");
		opCodes[126]=new OperateCode( "iand");
		opCodes[127]=new OperateCode( "land");
		opCodes[128]=new OperateCode( "ior");
		opCodes[129]=new OperateCode( "lor");
		opCodes[130]=new OperateCode( "ixor");
		opCodes[131]=new OperateCode( "lxor");
		opCodes[132]=new OperateCode( "iinc");
		opCodes[133]=new OperateCode( "i2l");
		opCodes[134]=new OperateCode( "i2f");
		opCodes[135]=new OperateCode( "i2d");
		opCodes[136]=new OperateCode( "l2i");
		opCodes[137]=new OperateCode( "l2f");
		opCodes[138]=new OperateCode( "l2d");
		opCodes[139]=new OperateCode( "f2i");
		opCodes[140]=new OperateCode( "f2l");
		opCodes[141]=new OperateCode( "f2d");
		opCodes[142]=new OperateCode( "d2i");
		opCodes[143]=new OperateCode( "d2l");
		opCodes[144]=new OperateCode( "d2f");
		opCodes[145]=new OperateCode( "i2b");
		opCodes[146]=new OperateCode( "i2c");
		opCodes[147]=new OperateCode( "i2s");
		opCodes[148]=new OperateCode( "lcmp");
		opCodes[149]=new OperateCode( "fcmpl");
		opCodes[150]=new OperateCode( "fcmpg");
		opCodes[151]=new OperateCode( "dcmpl");
		opCodes[152]=new OperateCode( "dcmpg");
		opCodes[153]=new OperateCode( "ifeq",OperandType.BRACH_OFFSET,2);
		opCodes[154]=new OperateCode( "ifne",OperandType.BRACH_OFFSET,2);
		opCodes[155]=new OperateCode( "iflt",OperandType.BRACH_OFFSET,2);
		opCodes[156]=new OperateCode( "ifge",OperandType.BRACH_OFFSET,2);
		opCodes[157]=new OperateCode( "ifgt",OperandType.BRACH_OFFSET,2);
		opCodes[158]=new OperateCode( "ifle",OperandType.BRACH_OFFSET,2);
		opCodes[159]=new OperateCode( "if_icmpeq",OperandType.BRACH_OFFSET,2);
		opCodes[160]=new OperateCode( "if_icmpne",OperandType.BRACH_OFFSET,2);
		opCodes[161]=new OperateCode( "if_icmplt",OperandType.BRACH_OFFSET,2);
		opCodes[162]=new OperateCode( "if_icmpge",OperandType.BRACH_OFFSET,2);
		opCodes[163]=new OperateCode( "if_icmpgt",OperandType.BRACH_OFFSET,2);
		opCodes[164]=new OperateCode( "if_icmple",OperandType.BRACH_OFFSET,2);
		opCodes[165]=new OperateCode( "if_acmpeq",OperandType.BRACH_OFFSET,2);
		opCodes[166]=new OperateCode( "if_acmpne",OperandType.BRACH_OFFSET,2);
		opCodes[167]=new OperateCode( "goto",OperandType.BRACH_OFFSET,2);
		opCodes[168]=new OperateCode( "jsr",OperandType.BRACH_OFFSET,2);
		opCodes[169]=new OperateCode( "ret",OperandType.LOCAL_VARIABLES_INDEX,1);
		opCodes[170]=new OperateCode( "tableswitch",OperandType.MUTABLE,-1);
		opCodes[171]=new OperateCode( "lookupswitch",OperandType.MUTABLE,-1);
		opCodes[172]=new OperateCode( "ireturn");
		opCodes[173]=new OperateCode( "lreturn");
		opCodes[174]=new OperateCode( "freturn");
		opCodes[175]=new OperateCode( "dreturn");
		opCodes[176]=new OperateCode( "areturn");
		opCodes[177]=new OperateCode( "return");
		opCodes[178]=new OperateCode( "getstatic",OperandType.CONSTANT_POOL_INDEX,2);
		opCodes[179]=new OperateCode( "putstatic",OperandType.CONSTANT_POOL_INDEX,2);
		opCodes[180]=new OperateCode( "getfield",OperandType.CONSTANT_POOL_INDEX,2);
		opCodes[181]=new OperateCode( "putfield",OperandType.CONSTANT_POOL_INDEX,2);
		opCodes[182]=new OperateCode( "invokevirtual",OperandType.CONSTANT_POOL_INDEX,2);
		opCodes[183]=new OperateCode( "invokespecial",OperandType.CONSTANT_POOL_INDEX,2);
		opCodes[184]=new OperateCode( "invokestatic",OperandType.CONSTANT_POOL_INDEX,2);
		opCodes[185]=new OperateCode( "invokeinterface",OperandType.CONSTANT_POOL_INDEX,2,OperandType.UNSIGNED_BYTE,1,OperandType.ZERO,1);
		opCodes[186]=new OperateCode( "invokedynamic",OperandType.CONSTANT_POOL_INDEX,2,OperandType.ZERO,1,OperandType.ZERO,1);
		opCodes[187]=new OperateCode( "new",OperandType.CONSTANT_POOL_INDEX,2);
		opCodes[188]=new OperateCode( "newarray",OperandType.UNSIGNED_BYTE,1);
		opCodes[189]=new OperateCode( "anewarray",OperandType.CONSTANT_POOL_INDEX,2);
		opCodes[190]=new OperateCode( "arraylength");
		opCodes[191]=new OperateCode( "athrow");
		opCodes[192]=new OperateCode( "checkcast",OperandType.CONSTANT_POOL_INDEX,2);
		opCodes[193]=new OperateCode( "instanceof",OperandType.CONSTANT_POOL_INDEX,2);
		opCodes[194]=new OperateCode( "monitorenter");
		opCodes[195]=new OperateCode( "monitorexit");
		opCodes[196]=new OperateCode( "wide",OperandType.MUTABLE,-1);
		opCodes[197]=new OperateCode( "multianewarray",OperandType.CONSTANT_POOL_INDEX,2,OperandType.UNSIGNED_BYTE,1);
		opCodes[198]=new OperateCode( "ifnull",OperandType.BRACH_OFFSET,2);
		opCodes[199]=new OperateCode( "ifnonnull",OperandType.BRACH_OFFSET,2);
		opCodes[200]=new OperateCode( "goto_w",OperandType.BRACH_OFFSET,4);
		opCodes[201]=new OperateCode( "jsr_w",OperandType.BRACH_OFFSET,4);
		opCodes[202]=new OperateCode( "breakpoint");
		opCodes[254]=new OperateCode( "impdep1");
		opCodes[255]=new OperateCode( "impdep2");


	}
}
